README.md
setup.py
kopeechka/__init__.py
kopeechka/async_mail_activations.py
kopeechka/async_methods.py
kopeechka/config.py
kopeechka/error.py
kopeechka/kopeechka_types.py
kopeechka/mail_activations.py
kopeechka/methods.py
kopeechka/module_log.py
kopeechka.egg-info/PKG-INFO
kopeechka.egg-info/SOURCES.txt
kopeechka.egg-info/dependency_links.txt
kopeechka.egg-info/requires.txt
kopeechka.egg-info/top_level.txt