Metadata-Version: 2.1
Name: kopeechka
Version: 7.0
Summary: This code is a representation of the kopeechka.store API in Python
Author-email: rem.game.on@gmail.com
Project-URL: Source, https://github.com/livvyyRUS/kopeechka
